magnet/__init__.py
magnet/config.py
magnet/config_test.py
magnet-1.1.1.dist-info/METADATA
magnet-1.1.1.dist-info/RECORD
magnet-1.1.1.dist-info/WHEEL
magnet-1.1.1.dist-info/top_level.txt
