Metadata-Version: 2.1
Name: magnet
Version: 1.1.1
Summary: Hierarchical YAML config reader that reads from multiple files and an environment variable
Home-page: https://gitlab.com/jeremija/pymagnet
Author: Jerko Steiner
Author-email: jerko.steiner@gmail.com
License: UNKNOWN
Platform: UNKNOWN
Classifier: Programming Language :: Python :: 3.5
Classifier: License :: OSI Approved :: MIT License
Classifier: Operating System :: OS Independent
Requires-Dist: PyYAML (>=3.12)
